[
  {
    "id": "531",
    "parentId": "0",
    "date": "2008-11-01 01:42:13",
    "content": "Возможно, я не прав, но врядле Гугл, даже вместе Бегун смогут вытеснить Яндекс, у них различные способы рейтингования.",
    "author": "Тарас",
    "authorSite": "http://www.5cs.ru/",
    "approved": true,
    "authorEmailMd5": "8c9ef968356edf48637209cd2fb69ec0"
  },
  {
    "id": "532",
    "parentId": "0",
    "date": "2008-11-01 17:48:47",
    "content": "Я имел ввиду рынок контекстной рекламы. Или вы имеете ввиду условия принятия сайтов в рекламную сеть?",
    "author": "Дима",
    "authorSite": "http://dimapolyakov.ru",
    "approved": true,
    "authorEmailMd5": "b36bc6a67a41870e7d8dc3dde55b671c"
  }
]