[
  {
    "id": "684",
    "parentId": "0",
    "date": "2009-02-11 23:30:32",
    "content": "Хорошо я не пользуюсь уже месяц аской ! Так что вряд ли попадусь ! Но все равно спасибо за информацию передам обязательно друзьям!",
    "author": "Маркетолог",
    "authorSite": "http://agent.rucontext.com/",
    "approved": true,
    "authorEmailMd5": "0e77efb5e507b980c19bfd68399e3649"
  },
  {
    "id": "685",
    "parentId": "0",
    "date": "2009-02-16 17:11:34",
    "content": "Icq умерает особенно с этим квипом. За Jabber&#39;ом будущее.",
    "author": "Инна",
    "authorSite": "http://an-stro-blog.ru/",
    "approved": true,
    "authorEmailMd5": "d23dcde649cde7f6f98c3f9c8aa9c7f0"
  },
  {
    "id": "686",
    "parentId": "0",
    "date": "2009-10-08 00:06:22",
    "content": "Сейчас другое рассылают, мол вы не пользуетесь давно и в чёрном списке отправьте смс на такой то номер",
    "author": "SpectrumSat",
    "authorSite": "",
    "approved": true,
    "authorEmailMd5": "d41d8cd98f00b204e9800998ecf8427e"
  },
  {
    "id": "687",
    "parentId": "0",
    "date": "2009-12-09 11:02:46",
    "content": "А ко мне добавлялись типо Админы и писали, что надо прислать сообщение на номер..., чтоб ваш вин не заблокировали. Я не попался на уловку. А сегодня в Аську не могу попасть(((Выдает ошибку",
    "author": "Дональд",
    "authorSite": "",
    "approved": true,
    "authorEmailMd5": "d41d8cd98f00b204e9800998ecf8427e"
  },
  {
    "id": "688",
    "parentId": "0",
    "date": "2009-12-22 22:06:21",
    "content": "у тебя наверно ася с хорошим номером! ячитала что так обычно делают чтоб узнать пароль!потом входят и меняют! мне тоже такое приходило хорошо денег на счету мало было! &#x1F60A;",
    "author": "светик",
    "authorSite": "",
    "approved": true,
    "authorEmailMd5": "8d5e7cd53716b9b568ab0ec8a6953eb6"
  },
  {
    "id": "689",
    "parentId": "0",
    "date": "2010-02-01 15:17:39",
    "content": "Кому нужна аська?Она мне надоела.Отдам юин даром.",
    "author": "Прохор",
    "authorSite": "",
    "approved": true,
    "authorEmailMd5": "d41d8cd98f00b204e9800998ecf8427e"
  },
  {
    "id": "690",
    "parentId": "0",
    "date": "2011-02-10 02:55:10",
    "content": "вышли если не жалко эмаил vasilevst@rambler.ru зарание благодарен Сергей",
    "author": "Сергей",
    "authorSite": "",
    "approved": true,
    "authorEmailMd5": "2edc3eb218bd862542d9740caf52083a"
  }
]