[
  {
    "id": "1437",
    "parentId": "0",
    "date": "2009-06-15 01:14:31",
    "content": "Тема &lt;body> не раскрыта &#x1F603",
    "author": "Стас",
    "authorSite": "",
    "approved": true,
    "authorEmailMd5": "d41d8cd98f00b204e9800998ecf8427e"
  },
  {
    "id": "1438",
    "parentId": "0",
    "date": "2009-06-15 03:05:20",
    "content": "Идея стара как мир на самом деле. Уже давно в голове пробегает мысля сделать себе такую.",
    "author": "almlex",
    "authorSite": "",
    "approved": true,
    "authorEmailMd5": "d41d8cd98f00b204e9800998ecf8427e"
  },
  {
    "id": "1439",
    "parentId": "0",
    "date": "2009-06-15 03:06:48",
    "content": "Ещё очень нужна кепочка с открывающим &lt;head>",
    "author": "almlex",
    "authorSite": "",
    "approved": true,
    "authorEmailMd5": "d41d8cd98f00b204e9800998ecf8427e"
  },
  {
    "id": "1440",
    "parentId": "0",
    "date": "2009-06-15 05:06:54",
    "content": "Господи, какой [:&#124;&#124;&#124;&#124;&#124;&#124;&#124;&#124;&#124;&#124;&#124;&#124;&#124;&#124;&#124;&#124;&#124;&#124;&#124;&#124;&#124;&#124;&#124;&#124;&#124;&#124;&#124;&#124;&#124;&#124;&#124;&#124;&#124;&#124;&#124;&#124;&#124;&#124;&#124;&#124;:]",
    "author": "Миша Абасов",
    "authorSite": "",
    "approved": true,
    "authorEmailMd5": "f4b2fa51c009b82c184f601282409556"
  },
  {
    "id": "1441",
    "parentId": "0",
    "date": "2009-06-15 10:10:38",
    "content": "&#x1F603 <br /> <b>Миша Абасов</b>,Видимо всех периодически посещают такие мысли <br /> <b>Стас</b>, верстку можно дополнить по желанию",
    "author": "Дмитрий",
    "authorSite": "http://dimapolyakov.ru",
    "approved": true,
    "authorEmailMd5": "b36bc6a67a41870e7d8dc3dde55b671c"
  },
  {
    "id": "1442",
    "parentId": "0",
    "date": "2009-06-15 11:29:00",
    "content": "Мммм... дизайн сменился? <br /> А маечка)) где т уже видела такую идейку <br /> (без обид)",
    "author": "kisuhvostik",
    "authorSite": "",
    "approved": true,
    "authorEmailMd5": "36aed15b84e2c943921b5a44acf16427"
  },
  {
    "id": "1443",
    "parentId": "0",
    "date": "2009-06-15 16:56:13",
    "content": "<blockquote class=\"quoteMessage\">где т уже видела такую идейку <br /> (без обид) </blockquote> <br /> конечно без обид. Видимо данная мысль посещает многих. <p> Где то видел футболку с облаком тегов на груди &#x1F60A;",
    "author": "Дмитрий",
    "authorSite": "http://dimapolyakov.ru",
    "approved": true,
    "authorEmailMd5": "b36bc6a67a41870e7d8dc3dde55b671c"
  },
  {
    "id": "1444",
    "parentId": "0",
    "date": "2009-07-14 01:00:46",
    "content": "Вообще такие футболки есть, по крайней мере с &lt;body> точно...сам видел.",
    "author": "Дэвид",
    "authorSite": "",
    "approved": true,
    "authorEmailMd5": "d41d8cd98f00b204e9800998ecf8427e"
  },
  {
    "id": "1445",
    "parentId": "0",
    "date": "2009-07-14 11:33:47",
    "content": "дайте ссылку, я закажу себе ))",
    "author": "Дмитрий",
    "authorSite": "http://dimapolyakov.ru",
    "approved": true,
    "authorEmailMd5": "b36bc6a67a41870e7d8dc3dde55b671c"
  },
  {
    "id": "1446",
    "parentId": "0",
    "date": "2009-10-26 08:55:42",
    "content": "http://www.thinkgeek.com/tshirts-apparel/unisex/generic/7804/",
    "author": "Jman",
    "authorSite": "",
    "approved": true,
    "authorEmailMd5": "a2bf72c57a8ead2a56ed7f794968437a"
  },
  {
    "id": "1447",
    "parentId": "1446",
    "date": "2009-10-26 10:07:10",
    "content": "Спасибо за ссылочку &#x1F609;",
    "author": "Дмитрий",
    "authorSite": "http://dimapolyakov.ru",
    "approved": true,
    "authorEmailMd5": "b36bc6a67a41870e7d8dc3dde55b671c"
  }
]