[
  {
    "id": "1707",
    "parentId": "0",
    "date": "2009-07-29 00:51:50",
    "content": "Ну то что запретили дом-2 это хорошо &#x1F603",
    "author": "MaxL",
    "authorSite": "",
    "approved": true,
    "authorEmailMd5": "d41d8cd98f00b204e9800998ecf8427e"
  },
  {
    "id": "1708",
    "parentId": "0",
    "date": "2009-07-29 03:05:27",
    "content": "а) абсолютно желтый заголовок. <br /> б) его будут и дальше показывать, только позже. <br /> в) Счастливы вместе нормальный сериал.",
    "author": "Миша Абасов",
    "authorSite": "",
    "approved": true,
    "authorEmailMd5": "f4b2fa51c009b82c184f601282409556"
  },
  {
    "id": "1709",
    "parentId": "0",
    "date": "2009-07-29 06:50:07",
    "content": "канечно не в тему <br /> http://clip2net.com/page/m0/1470432",
    "author": "-=FoX=-",
    "authorSite": "",
    "approved": true,
    "authorEmailMd5": "d41d8cd98f00b204e9800998ecf8427e"
  },
  {
    "id": "1710",
    "parentId": "1709",
    "date": "2009-07-29 09:36:52",
    "content": "таки задумывалось &#x1F60A; <br /> Наверно надо написать <b>%ЮзерНейм%</b>",
    "author": "Дмитрий",
    "authorSite": "http://dimapolyakov.ru",
    "approved": true,
    "authorEmailMd5": "b36bc6a67a41870e7d8dc3dde55b671c"
  },
  {
    "id": "1711",
    "parentId": "1708",
    "date": "2009-07-29 09:39:02",
    "content": "а) не скрываю. Тут хитрый расчет. <br /> б) ну всё же ограничение существенное. Помню одно время его показывали раз 3 в день. Прям как выпуски новостей. <br /> в) на вкус и цвет &#x1F609;",
    "author": "Дмитрий",
    "authorSite": "http://dimapolyakov.ru",
    "approved": true,
    "authorEmailMd5": "b36bc6a67a41870e7d8dc3dde55b671c"
  },
  {
    "id": "1712",
    "parentId": "0",
    "date": "2009-07-29 10:11:55",
    "content": "Очень рада, что дом2 запретили! <br /> А Букины... пошлый сериал о муже-неудачнике и глупой жене - <br /> неудачная попытка русских &quot;слизать&quot; сюжет с забугорного сериала((",
    "author": "kisuhvostik",
    "authorSite": "",
    "approved": true,
    "authorEmailMd5": "36aed15b84e2c943921b5a44acf16427"
  },
  {
    "id": "1713",
    "parentId": "0",
    "date": "2009-07-29 11:52:30",
    "content": "&quot;А ведь это смотрят сегодняшние подростки.&quot; - Я подросток но не смотрю такое гавно как &quot;телевизор&quot;.....",
    "author": "Duck4Fuck",
    "authorSite": "",
    "approved": true,
    "authorEmailMd5": "8b7188e3018aac77faa296206ccd344a"
  },
  {
    "id": "1714",
    "parentId": "0",
    "date": "2009-07-29 12:09:13",
    "content": "Херня это все. и «Дом-2» будут показывать до тех пор, пока он приносит деньги. <br /> Да и что вы так все на него взъелись то? Все такие высоконравственные? <br /> А то, что все это смотрят подростки и учатся у них — это просто жесть. Если подросток, извиняюсь за выражение, мудак, то он и наркомана на улице увидит и захочет тогда ширнутся. <br /> Я допустим, когда делать нечего, даже смотрю этот «Дом-2». И дкело не в том, что он мне нравится, когда я его смотрю — я не заморачиваюсь, просто смотрю для фона, поржать над ними. <p> Счастливы вместе — аналогично. Только детям младшего школьного возраста все-таки не стоит показывать.",
    "author": "Максимушка",
    "authorSite": "",
    "approved": true,
    "authorEmailMd5": "d41d8cd98f00b204e9800998ecf8427e"
  },
  {
    "id": "1715",
    "parentId": "0",
    "date": "2009-07-29 13:24:32",
    "content": "<b>Максимушка</b>, честно, мне противно, что показывают в этом реалити-шоу. Но периодически его смотрит сестра и даже не смотря, а просто слыша их диалоги начинает воротить. <p> P.S. Как то на баше было: <p> <blockquote class=\"quoteMessage\">Народ, а кто нибудь еще помнит что в первом Доме на ТНТ люди РЕАЛЬНО СТРОИЛИ дом</blockquote>",
    "author": "Дмитрий",
    "authorSite": "http://dimapolyakov.ru",
    "approved": true,
    "authorEmailMd5": "b36bc6a67a41870e7d8dc3dde55b671c"
  },
  {
    "id": "1716",
    "parentId": "0",
    "date": "2009-07-29 17:46:13",
    "content": "Если его запретили, то почему сейчас в 21.00 (17.00 по москве) он спокойно идет на тнт? Когда запрет вступит в силу?",
    "author": "Финк",
    "authorSite": "",
    "approved": true,
    "authorEmailMd5": "8ecda82804db1a179711afc42e031c58"
  },
  {
    "id": "1717",
    "parentId": "1716",
    "date": "2009-07-29 18:03:16",
    "content": "<b>Финк</b>, попробую уточнить",
    "author": "Дмитрий",
    "authorSite": "http://dimapolyakov.ru",
    "approved": true,
    "authorEmailMd5": "b36bc6a67a41870e7d8dc3dde55b671c"
  },
  {
    "id": "1718",
    "parentId": "0",
    "date": "2009-07-29 22:28:37",
    "content": "Счастливы вместе супер сериал!!!а укого не хватает серого вещества понять его можете просто тупо не смотреть его Я не спорю конечно лучше сесть и посмотреть Вечная любовь...Кармелита и прочие &quot;отличные&quot; серилы после 1 минуты просмотра которых мозг на стену рвет аж",
    "author": "александр",
    "authorSite": "",
    "approved": true,
    "authorEmailMd5": "d41d8cd98f00b204e9800998ecf8427e"
  },
  {
    "id": "1719",
    "parentId": "1718",
    "date": "2009-07-29 22:56:53",
    "content": "все вами приведенные сериалы - одного поле ягоды! <p> Немного более лучший - Универ. Смотрю иногда. А так даже вспомнить не могу сериала, который я бы обязательно смотрел. Спецназ разве чтоль, который по первому каналу был. Ну и многосерийные фильмы о войне.",
    "author": "Дмитрий",
    "authorSite": "http://dimapolyakov.ru",
    "approved": true,
    "authorEmailMd5": "b36bc6a67a41870e7d8dc3dde55b671c"
  },
  {
    "id": "1720",
    "parentId": "0",
    "date": "2009-07-31 00:59:30",
    "content": "Нуууу... В общем не вполне своевременный, но явно ожидаемый PR-ход ТНТ. IMXO &#x1F60A;",
    "author": "ratvva",
    "authorSite": "",
    "approved": true,
    "authorEmailMd5": "af98881e7b41fed05fd23fa7a87a6665"
  },
  {
    "id": "1721",
    "parentId": "0",
    "date": "2009-07-31 21:51:04",
    "content": "Запретить то запретили, а все равно показывают...видимо взятку кому-то дали... 😢",
    "author": "Стас",
    "authorSite": "",
    "approved": true,
    "authorEmailMd5": "d74de694d12547fdceec4f8418150f86"
  },
  {
    "id": "1722",
    "parentId": "1715",
    "date": "2009-08-03 13:20:21",
    "content": "Аха... было такое)",
    "author": "Дмитрий Шишкин",
    "authorSite": "http://shugich.ru",
    "approved": true,
    "authorEmailMd5": "d41d8cd98f00b204e9800998ecf8427e"
  },
  {
    "id": "1723",
    "parentId": "1718",
    "date": "2009-08-04 20:49:52",
    "content": "Все наши популярные сериалы это под копирку слизанные иностранные. Несколько примеров: <br /> Не родись красивой = Ugly Betty <br /> Счастливы вместе = Married… with Children <br /> А сейчас у нас делают ещё и копию House M.D. Вот что реально стоит смотреть из сериалов так это такие сериалы как LOST, Heroes, Lie To Me, The Big Bang Theory, Dexter, Prison Break, House M.D.",
    "author": "Александр",
    "authorSite": "http://almlog.ucoz.ru",
    "approved": true,
    "authorEmailMd5": "d41d8cd98f00b204e9800998ecf8427e"
  },
  {
    "id": "1724",
    "parentId": "1723",
    "date": "2009-08-05 10:31:05",
    "content": "Все верно. Какой сериал аналог какого узнаю на vokrug.tv",
    "author": "Дмитрий",
    "authorSite": "http://dimapolyakov.ru",
    "approved": true,
    "authorEmailMd5": "b36bc6a67a41870e7d8dc3dde55b671c"
  },
  {
    "id": "1725",
    "parentId": "1723",
    "date": "2009-08-06 10:10:49",
    "content": "Еще и нашу рашу позаимствовали. Это, правда, не совсем сериал. <br /> Наша раша = Маленькая британия (посмотрите хотя бы вступление, все сразу ясно станет)",
    "author": "",
    "authorSite": "http://win-design.org/",
    "approved": true,
    "authorEmailMd5": "d41d8cd98f00b204e9800998ecf8427e"
  },
  {
    "id": "1726",
    "parentId": "0",
    "date": "2009-08-07 23:20:36",
    "content": "Это пиар ход. Даже уже не интересно. Что это тупость - понятно. Но хотя бы РЖАЧНАЯ тупость. А дети, которые смотрят... Ну найдут Дому2 замену. И не факт, что эта самая замена будет лучше, родители может еще выть будут, верните Дом ребенок порнуху стал смотреть.",
    "author": "ЛюБка",
    "authorSite": "",
    "approved": true,
    "authorEmailMd5": "b0cc67ac96e457f2ccec92d7b3067afc"
  },
  {
    "id": "1727",
    "parentId": "0",
    "date": "2009-10-27 14:14:17",
    "content": "Hу очень радует, может его окончательно запретят???",
    "author": "Kis-kis",
    "authorSite": "",
    "approved": true,
    "authorEmailMd5": "186dcc832c1c26ac9c846f9c622e95f8"
  },
  {
    "id": "1728",
    "parentId": "0",
    "date": "2009-10-27 14:15:42",
    "content": "Очень радует))) &#x1F603",
    "author": "Kis-kis",
    "authorSite": "",
    "approved": true,
    "authorEmailMd5": "186dcc832c1c26ac9c846f9c622e95f8"
  }
]