[
  {
    "id": "1754",
    "parentId": "0",
    "date": "2009-08-09 13:43:57",
    "content": "habr рулит - там новость быстрей появилась &#x1F603",
    "author": "MaxL",
    "authorSite": "",
    "approved": true,
    "authorEmailMd5": "d41d8cd98f00b204e9800998ecf8427e"
  },
  {
    "id": "1755",
    "parentId": "1754",
    "date": "2009-08-09 14:06:57",
    "content": "Ну с хабром вообще сложно тягаться &#x1F603 <br /> Пост скорее для тех, кто хабр не читает.",
    "author": "Дмитрий",
    "authorSite": "http://dimapolyakov.ru",
    "approved": true,
    "authorEmailMd5": "b36bc6a67a41870e7d8dc3dde55b671c"
  },
  {
    "id": "1756",
    "parentId": "0",
    "date": "2009-08-09 19:17:52",
    "content": "Дим Др.Веб не сел как Нод32 и Касперский <p> ЗЫ я не читаю хабр &#x1F603",
    "author": "OnMusic",
    "authorSite": "",
    "approved": true,
    "authorEmailMd5": "d41d8cd98f00b204e9800998ecf8427e"
  },
  {
    "id": "1757",
    "parentId": "1756",
    "date": "2009-08-09 19:40:05",
    "content": "Не понял твоего коммента 😳 <p> &quot;не сел&quot; в смысле не силён? <br /> Тогда я в корне не согласен! Я постоянный пользователь др. веба со стажем (более 3 лет) и <b>ни разу он меня не подвел</b>. <br /> А вот с нодом была неприятная ситуация.лечил в одной конторе компы. Лицензионный нод, обновляю, проверяю - ничего не находит. Запускаю CureIt! от веба - на компе просто зоопарк.",
    "author": "Дмитрий",
    "authorSite": "http://dimapolyakov.ru",
    "approved": true,
    "authorEmailMd5": "b36bc6a67a41870e7d8dc3dde55b671c"
  },
  {
    "id": "1758",
    "parentId": "0",
    "date": "2009-08-10 02:22:11",
    "content": "ДА силен он, у меня было дохера вирусов я доверился ему, а это др веб мне винду сломал, теперь у меня другая винда и я доверяю ноду и касперскому",
    "author": "OnMusic",
    "authorSite": "",
    "approved": true,
    "authorEmailMd5": "d41d8cd98f00b204e9800998ecf8427e"
  },
  {
    "id": "1759",
    "parentId": "0",
    "date": "2009-08-10 09:33:04",
    "content": "*Пошёл тырить ключи*",
    "author": "zox",
    "authorSite": "",
    "approved": true,
    "authorEmailMd5": "d41d8cd98f00b204e9800998ecf8427e"
  },
  {
    "id": "1760",
    "parentId": "1758",
    "date": "2009-08-10 11:19:09",
    "content": "ржунимагу",
    "author": "Дмитрий",
    "authorSite": "http://dimapolyakov.ru",
    "approved": true,
    "authorEmailMd5": "b36bc6a67a41870e7d8dc3dde55b671c"
  },
  {
    "id": "1761",
    "parentId": "0",
    "date": "2009-08-10 21:15:18",
    "content": "<b>Яхоооу!</b> У меня теперь ключ до конца августа 2012 года! <br /> Интересно, как я это сделал?",
    "author": "Дмитрий",
    "authorSite": "http://dimapolyakov.ru",
    "approved": true,
    "authorEmailMd5": "b36bc6a67a41870e7d8dc3dde55b671c"
  },
  {
    "id": "1762",
    "parentId": "0",
    "date": "2009-08-20 02:18:26",
    "content": "Даешь серийник на мыло =)",
    "author": "mob_dp",
    "authorSite": "",
    "approved": true,
    "authorEmailMd5": "9c1747f9df437a3cd30b3dea29787f13"
  },
  {
    "id": "1763",
    "parentId": "0",
    "date": "2009-10-09 19:19:37",
    "content": "а мне пишут, что получить код невозможно из другой страны, что делать?",
    "author": "Сергей",
    "authorSite": "",
    "approved": true,
    "authorEmailMd5": "85c0274fedea7a38b8a2468192c9969f"
  },
  {
    "id": "1764",
    "parentId": "0",
    "date": "2010-10-10 21:57:58",
    "content": "привет Дима, <br /> скинь плиз ключик(если случайно завалялся где нить)на мыло(или линк), а то акция закончилась ...",
    "author": "Ronin",
    "authorSite": "",
    "approved": true,
    "authorEmailMd5": "6c3be672b3e3a83610a82e34aee27865"
  }
]