[
  {
    "id": "7",
    "parentId": "0",
    "date": "2008-03-13 17:59:20",
    "content": "Привет. <br /> Сайт наверное нормальный, но какой злой гений придумал продавать это в смоленске по ценам, которые дороже розничных магазинов? <br /> к тебе претензий нет - веб2.0 рулит :) но сама идея полный пипец! интересно, с начала открытия они продали больше 10 бутыльков или меньше??? <p> на самом деле просто интересно стало - я тоже дима, дизайнер и родился 10 сентября, только 1985 года :)",
    "author": "Дима",
    "authorSite": "",
    "approved": true,
    "authorEmailMd5": "d41d8cd98f00b204e9800998ecf8427e"
  },
  {
    "id": "8",
    "parentId": "0",
    "date": "2008-03-18 23:44:31",
    "content": "Ну на сколько я знаю, продажи нормальные. Но, как сам понимаешь, на ценовую политику я не влияю. Сейчас готовлю модернизацию сайта, так что будет всё ещё круче &#x1F603",
    "author": "Дмитрий",
    "authorSite": "http://dimapolyakov.ru",
    "approved": true,
    "authorEmailMd5": "b36bc6a67a41870e7d8dc3dde55b671c"
  }
]